airpyllution/__init__.py
airpyllution/airpyllution.py
airpyllution/utils.py
airpyllution-2.0.1.dist-info/LICENSE
airpyllution-2.0.1.dist-info/WHEEL
airpyllution-2.0.1.dist-info/METADATA
airpyllution-2.0.1.dist-info/RECORD
