Metadata-Version: 2.1
Name: airpyllution
Version: 2.0.1
Summary: A package which  provides various functionalities on air pollution data.
License: MIT
Author: Christopher Alexander, Daniel King, Mel Liow
Requires-Python: >=3.9,<4.0
Classifier: License :: OSI Approved :: MIT License
Classifier: Programming Language :: Python :: 3
Classifier: Programming Language :: Python :: 3.10
Classifier: Programming Language :: Python :: 3.9
Requires-Dist: DateTime (>=4.3,<5.0)
Requires-Dist: altair (>=4.2.0,<5.0.0)
Requires-Dist: altair-viewer (>=0.4.0,<0.5.0)
Requires-Dist: black (>=21.12b0,<22.0)
Requires-Dist: mock (>=4.0.3,<5.0.0)
Requires-Dist: numpy (>=1.22.1,<2.0.0)
Requires-Dist: pandas (>=1.3.5,<2.0.0)
Requires-Dist: plotly (>=5.5.0,<6.0.0)
Requires-Dist: python-dotenv (>=0.19.2,<0.20.0)
Requires-Dist: requests (>=2.27.1,<3.0.0)
Requires-Dist: responses (>=0.17.0,<0.18.0)
Requires-Dist: vega-datasets (>=0.9.0,<0.10.0)
